cord_workflow_controller_client
