Metadata-Version: 1.1
Name: cord-workflow-controller-client
Version: 0.1.1
Summary: A client library for CORD Workflow Controller
Home-page: https://gerrit.opencord.org/gitweb?p=cord-workflow-controller-client.git
Author: Illyoung Choi
Author-email: iychoi@opennetworking.org
License: Apache v2
Platform: UNKNOWN
Classifier: License :: OSI Approved :: Apache Software License
